.gitignore
LICENSE
__init__.py
setup.py
soundex.html
soundex/__init__.py
soundex/charmap.py
soundex/core.py
soundex.egg-info/PKG-INFO
soundex.egg-info/SOURCES.txt
soundex.egg-info/dependency_links.txt
soundex.egg-info/not-zip-safe
soundex.egg-info/requires.txt
soundex.egg-info/top_level.txt
soundex/templates/soundex.html