Metadata-Version: 1.0
Name: soundex
Version: 0.3.1
Summary: Soundex Phonetic Code Algorithm for Indian Languages
Home-page: http://silpa.org.in/Soundex
Author: Santhosh Thottingal
Author-email: santhosh.thottingal@gmail.com
License: LGPL-3.0
Platform: UNKNOWN
